streamviz.py
streamviz-5.0.dist-info/LICENSE
streamviz-5.0.dist-info/WHEEL
streamviz-5.0.dist-info/METADATA
streamviz-5.0.dist-info/RECORD
