Metadata-Version: 2.1
Name: streamviz
Version: 5.0
Summary: Custom Plotly visualizations for Streamlit
Author-email: Derek Evans <derek.evans@deinfoservice.com>
Requires-Dist: streamlit
Requires-Dist: plotly
Project-URL: Demo, https://stream-gauge.streamlit.app/
Project-URL: Home, https://www.techbyderek.com
Project-URL: Repository, https://github.com/REPNOT/streamviz
